{
    "head": "head",
    "portraitScale": 0.8,
    "portraitTranslation": [ 0, 0.1, 0 ],
    "profileScale": 0.9,
    "profileTranslation": [ 0, 0.2, 0 ],
    "faint": "bedrock(ariadosslayer, sleep)",
    "poses": {
      "standing": {
        "poseName": "standing",
        "transformTicks": 10,
        "poseTypes": [
          "STAND",
          "NONE",
          "PORTRAIT",
          "PROFILE"
        ],
        "animations": [
          "look",
      "bedrock(ariadosslayer, ground_idle)"
        ]
      },
      "sleeping": {
        "poseName": "sleeping",
        "transformTicks": 10,
        "poseTypes": [ "SLEEP" ],
        "animations": [ "bedrock(ariadosslayer, sleep)" ]
      },
      "walking": {
        "poseName": "walking",
        "transformTicks": 10,
        "poseTypes": [ "WALK" ],
        "animations": [ "bedrock(ariadosslayer, ground_walk)" ]
      }
      
	}
  }