{
	"format_version": "1.8.0",
	"animations": {
		"pose": {
			"loop": true,
			"bones": {
				"iron_crown2": {
					"position": [0, 4, 0]
				},
				"leg_left_back": {
					"position": [0, -2, 0]
				},
				"leg_left_back2": {
					"rotation": [17.75313, -9.53274, -3.03513]
				},
				"leg_right_back": {
					"position": [0, -2, 0]
				},
				"leg_left_front": {
					"rotation": [-13.05005, -14.52675, -6.67752]
				},
				"leg_left_front2": {
					"rotation": [43.25, 0, 0],
					"position": [0, 0, 0]
				},
				"leg_left_front3": {
					"rotation": [47.5, 0, 0]
				},
				"leg_right_front2": {
					"rotation": [4.98635, -2.41476, 0.64743]
				},
				"ass": {
					"rotation": [-7.5, 0, 0]
				},
				"horn_right_2": {
					"rotation": [-55, 0, 0]
				},
				"horn_right_1": {
					"rotation": [-29.78729, -3.74196, -6.50446]
				},
				"horn_right_3": {
					"rotation": [47.5, 0, 0]
				},
				"horn_right_4": {
					"rotation": [-47.5, 0, 0]
				},
				"horn_left_1": {
					"rotation": [-29.78729, 3.74196, 6.50446]
				},
				"horn_left_2": {
					"rotation": [-55, 0, 0]
				},
				"horn_left_3": {
					"rotation": [47.5, 0, 0]
				},
				"horn_left_4": {
					"rotation": [-47.46404, 1.2834, -2.07937]
				},
				"collar": {
					"position": [0, 0, 0]
				},
				"neck": {
					"position": [0, 0, 0]
				},
				"leg_right_back3": {
					"position": [0, 0, 0]
				},
				"leg_right_front3": {
					"rotation": [-5, 0, 0],
					"position": [0, 0, 0]
				},
				"mouth": {
					"rotation": [0, 0, 0]
				}
			}
		},
		"animation.ironcrown.ground_idle": {
			"loop": true,
			"bones": {
				"iron_crown2": {
					"position": [0, 4, 0]
				},
				"leg_left_back": {
					"position": [0, -2, 0]
				},
				"leg_left_back2": {
					"rotation": [17.75313, -9.53274, -3.03513]
				},
				"leg_right_back": {
					"position": [0, -2, 0]
				},
				"leg_left_front": {
					"rotation": [-13.05005, -14.52675, -6.67752]
				},
				"leg_left_front2": {
					"rotation": [43.25, 0, 0],
					"position": [0, 0, 0]
				},
				"leg_left_front3": {
					"rotation": [47.5, 0, 0]
				},
				"leg_right_front2": {
					"rotation": [4.98635, -2.41476, 0.64743]
				},
				"ass": {
					"rotation": [-7.5, 0, 0]
				},
				"horn_right_2": {
					"rotation": [-55, 0, 0]
				},
				"horn_right_1": {
					"rotation": [-29.78729, -3.74196, -6.50446]
				},
				"horn_right_3": {
					"rotation": [47.5, 0, 0]
				},
				"horn_right_4": {
					"rotation": [-47.5, 0, 0]
				},
				"horn_left_1": {
					"rotation": [-29.78729, 3.74196, 6.50446]
				},
				"horn_left_2": {
					"rotation": [-55, 0, 0]
				},
				"horn_left_3": {
					"rotation": [47.5, 0, 0]
				},
				"horn_left_4": {
					"rotation": [-47.46404, 1.2834, -2.07937]
				},
				"collar": {
					"position": [0, 0, 0]
				},
				"neck": {
					"position": [0, 0, 0]
				},
				"leg_right_back3": {
					"position": [0, 0, 0]
				},
				"leg_right_front3": {
					"rotation": [-5, 0, 0],
					"position": [0, 0, 0]
				},
				"mouth": {
					"rotation": [0, 0, 0]
				}
			}
		},
		"animation.ironcrown.ground_walk": {
			"loop": true,
			"bones": {
				"iron_crown2": {
					"position": [0, 4, 0]
				},
				"leg_left_back": {
					"position": [0, -2, 0]
				},
				"leg_left_back2": {
					"rotation": [17.75313, -9.53274, -3.03513]
				},
				"leg_right_back": {
					"position": [0, -2, 0]
				},
				"leg_left_front": {
					"rotation": [-13.05005, -14.52675, -6.67752]
				},
				"leg_left_front2": {
					"rotation": [43.25, 0, 0],
					"position": [0, 0, 0]
				},
				"leg_left_front3": {
					"rotation": [47.5, 0, 0]
				},
				"leg_right_front2": {
					"rotation": [4.98635, -2.41476, 0.64743]
				},
				"ass": {
					"rotation": [-7.5, 0, 0]
				},
				"horn_right_2": {
					"rotation": [-55, 0, 0]
				},
				"horn_right_1": {
					"rotation": [-29.78729, -3.74196, -6.50446]
				},
				"horn_right_3": {
					"rotation": [47.5, 0, 0]
				},
				"horn_right_4": {
					"rotation": [-47.5, 0, 0]
				},
				"horn_left_1": {
					"rotation": [-29.78729, 3.74196, 6.50446]
				},
				"horn_left_2": {
					"rotation": [-55, 0, 0]
				},
				"horn_left_3": {
					"rotation": [47.5, 0, 0]
				},
				"horn_left_4": {
					"rotation": [-47.46404, 1.2834, -2.07937]
				},
				"collar": {
					"position": [0, 0, 0]
				},
				"neck": {
					"position": [0, 0, 0]
				},
				"leg_right_back3": {
					"position": [0, 0, 0]
				},
				"leg_right_front3": {
					"rotation": [-5, 0, 0],
					"position": [0, 0, 0]
				},
				"mouth": {
					"rotation": [0, 0, 0]
				}
			}
		}
	}
}