{
	"format_version": "1.12.0",
	"minecraft:geometry": [
		{
			"description": {
				"identifier": "geometry.octillery",
				"texture_width": 64,
				"texture_height": 64,
				"visible_bounds_width": 4,
				"visible_bounds_height": 2.5,
				"visible_bounds_offset": [0, 0.75, 0]
			},
			"bones": [
				{
					"name": "octillery",
					"pivot": [0, 0, 0]
				},
				{
					"name": "body",
					"parent": "octillery",
					"pivot": [0, 1, 0],
					"cubes": [
						{"origin": [-4, 0, -4], "size": [8, 5, 8], "uv": [0, 16]}
					]
				},
				{
					"name": "tentacles",
					"parent": "body",
					"pivot": [0, 2.1, 0],
					"rotation": [0, 45, 0]
				},
				{
					"name": "front_left",
					"parent": "tentacles",
					"pivot": [5.6, 0.1, 0],
					"rotation": [0, 7.5, 0],
					"cubes": [
						{"origin": [3.6, 0.1, -2], "size": [6, 4, 4], "uv": [24, 0]}
					]
				},
				{
					"name": "front_left2",
					"parent": "front_left",
					"pivot": [9.1, 0.1, 0],
					"cubes": [
						{"origin": [9.1, 0.1, -1.5], "size": [4, 3, 3], "uv": [14, 41]}
					]
				},
				{
					"name": "front_left3",
					"parent": "front_left2",
					"pivot": [12.1, 0.1, 0],
					"cubes": [
						{"origin": [12.1, 0.1, -1], "size": [4, 2, 2], "uv": [40, 0]}
					]
				},
				{
					"name": "nub2",
					"parent": "front_left3",
					"pivot": [12.6, 0.1, 0],
					"cubes": [
						{"origin": [13.6, -0.4, -1], "size": [2, 2, 2], "inflate": -0.1, "uv": [8, 46]}
					]
				},
				{
					"name": "nub5",
					"parent": "front_left2",
					"pivot": [9.1, 0.1, 0],
					"cubes": [
						{"origin": [10.1, -0.4, -1], "size": [2, 2, 2], "uv": [0, 0]}
					]
				},
				{
					"name": "back_left",
					"parent": "tentacles",
					"pivot": [0, 0.1, 5.6],
					"cubes": [
						{"origin": [-2, 0.1, 3.6], "size": [4, 4, 6], "uv": [26, 23]}
					]
				},
				{
					"name": "back_left2",
					"parent": "back_left",
					"pivot": [0, 0.1, 9.1],
					"cubes": [
						{"origin": [-1.5, 0.1, 9.1], "size": [3, 3, 4], "uv": [36, 37]}
					]
				},
				{
					"name": "back_left3",
					"parent": "back_left2",
					"pivot": [0, 0.1, 12.1],
					"cubes": [
						{"origin": [-1, 0.1, 12.1], "size": [2, 2, 4], "uv": [28, 41]}
					]
				},
				{
					"name": "nub3",
					"parent": "back_left3",
					"pivot": [0, -0.4, 14.6],
					"cubes": [
						{"origin": [-1, -0.4, 13.6], "size": [2, 2, 2], "inflate": -0.1, "uv": [46, 26]}
					]
				},
				{
					"name": "nub6",
					"parent": "back_left2",
					"pivot": [0, 0.1, 9.1],
					"cubes": [
						{"origin": [-1, -0.4, 10.1], "size": [2, 2, 2], "uv": [24, 20]}
					]
				},
				{
					"name": "back_left4",
					"parent": "tentacles",
					"pivot": [0, 0, 0],
					"rotation": [0, 45, 0],
					"cubes": [
						{"origin": [-2, 0.1, 3.6], "size": [4, 4, 6], "uv": [26, 23]}
					]
				},
				{
					"name": "back_left5",
					"parent": "back_left4",
					"pivot": [0, 0.1, 9.1],
					"cubes": [
						{"origin": [-1.5, 0.1, 9.1], "size": [3, 3, 4], "uv": [36, 37]}
					]
				},
				{
					"name": "back_left6",
					"parent": "back_left5",
					"pivot": [0, 0.1, 12.1],
					"cubes": [
						{"origin": [-1, 0.1, 12.1], "size": [2, 2, 4], "uv": [28, 41]}
					]
				},
				{
					"name": "nub9",
					"parent": "back_left6",
					"pivot": [0, -0.4, 14.6],
					"cubes": [
						{"origin": [-1, -0.4, 13.6], "size": [2, 2, 2], "inflate": -0.1, "uv": [46, 26]}
					]
				},
				{
					"name": "nub10",
					"parent": "back_left5",
					"pivot": [0, 0.1, 9.1],
					"cubes": [
						{"origin": [-1, -0.4, 10.1], "size": [2, 2, 2], "uv": [24, 20]}
					]
				},
				{
					"name": "back_left7",
					"parent": "tentacles",
					"pivot": [0, 0, 0],
					"rotation": [0, -25, 0],
					"cubes": [
						{"origin": [-2, 0.1, 3.6], "size": [4, 4, 6], "uv": [26, 23]}
					]
				},
				{
					"name": "back_left8",
					"parent": "back_left7",
					"pivot": [0, 0.1, 9.1],
					"cubes": [
						{"origin": [-1.5, 0.1, 9.1], "size": [3, 3, 4], "uv": [36, 37]}
					]
				},
				{
					"name": "back_left9",
					"parent": "back_left8",
					"pivot": [0, 0.1, 12.1],
					"cubes": [
						{"origin": [-1, 0.1, 12.1], "size": [2, 2, 4], "uv": [28, 41]}
					]
				},
				{
					"name": "nub13",
					"parent": "back_left9",
					"pivot": [0, -0.4, 14.6],
					"cubes": [
						{"origin": [-1, -0.4, 13.6], "size": [2, 2, 2], "inflate": -0.1, "uv": [46, 26]}
					]
				},
				{
					"name": "nub14",
					"parent": "back_left8",
					"pivot": [0, 0.1, 9.1],
					"cubes": [
						{"origin": [-1, -0.4, 10.1], "size": [2, 2, 2], "uv": [24, 20]}
					]
				},
				{
					"name": "back_right",
					"parent": "tentacles",
					"pivot": [-5.6, 0.1, 0],
					"cubes": [
						{"origin": [-9.6, 0.1, -2], "size": [6, 4, 4], "uv": [20, 33]}
					]
				},
				{
					"name": "back_right2",
					"parent": "back_right",
					"pivot": [-9.1, 0.1, 0],
					"cubes": [
						{"origin": [-13.1, 0.1, -1.5], "size": [4, 3, 3], "uv": [40, 20]}
					]
				},
				{
					"name": "back_right3",
					"parent": "back_right2",
					"pivot": [-12.1, 0.1, 0],
					"cubes": [
						{"origin": [-16.1, 0.1, -1], "size": [4, 2, 2], "uv": [14, 29]}
					]
				},
				{
					"name": "nub4",
					"parent": "back_right3",
					"pivot": [-12.6, 0.1, 0],
					"cubes": [
						{"origin": [-15.6, -0.4, -1], "size": [2, 2, 2], "inflate": -0.1, "uv": [0, 46]}
					]
				},
				{
					"name": "nub7",
					"parent": "back_right2",
					"pivot": [-9.1, 0.1, 0],
					"cubes": [
						{"origin": [-12.1, -0.4, -1], "size": [2, 2, 2], "uv": [44, 10]}
					]
				},
				{
					"name": "back_right4",
					"parent": "tentacles",
					"pivot": [0, 0, 0],
					"rotation": [0, -45, 0],
					"cubes": [
						{"origin": [-9.6, 0.1, -2], "size": [6, 4, 4], "uv": [20, 33]}
					]
				},
				{
					"name": "back_right5",
					"parent": "back_right4",
					"pivot": [-9.1, 0.1, 0],
					"cubes": [
						{"origin": [-13.1, 0.1, -1.5], "size": [4, 3, 3], "uv": [40, 20]}
					]
				},
				{
					"name": "back_right6",
					"parent": "back_right5",
					"pivot": [-12.1, 0.1, 0],
					"cubes": [
						{"origin": [-16.1, 0.1, -1], "size": [4, 2, 2], "uv": [14, 29]}
					]
				},
				{
					"name": "nub11",
					"parent": "back_right6",
					"pivot": [-12.6, 0.1, 0],
					"cubes": [
						{"origin": [-15.6, -0.4, -1], "size": [2, 2, 2], "inflate": -0.1, "uv": [0, 46]}
					]
				},
				{
					"name": "nub12",
					"parent": "back_right5",
					"pivot": [-9.1, 0.1, 0],
					"cubes": [
						{"origin": [-12.1, -0.4, -1], "size": [2, 2, 2], "uv": [44, 10]}
					]
				},
				{
					"name": "back_right7",
					"parent": "tentacles",
					"pivot": [0, 0, 0],
					"rotation": [0, 25, 0],
					"cubes": [
						{"origin": [-9.6, 0.1, -2], "size": [6, 4, 4], "uv": [20, 33]}
					]
				},
				{
					"name": "back_right8",
					"parent": "back_right7",
					"pivot": [-9.1, 0.1, 0],
					"cubes": [
						{"origin": [-13.1, 0.1, -1.5], "size": [4, 3, 3], "uv": [40, 20]}
					]
				},
				{
					"name": "back_right9",
					"parent": "back_right8",
					"pivot": [-12.1, 0.1, 0],
					"cubes": [
						{"origin": [-16.1, 0.1, -1], "size": [4, 2, 2], "uv": [14, 29]}
					]
				},
				{
					"name": "nub15",
					"parent": "back_right9",
					"pivot": [-12.6, 0.1, 0],
					"cubes": [
						{"origin": [-15.6, -0.4, -1], "size": [2, 2, 2], "inflate": -0.1, "uv": [0, 46]}
					]
				},
				{
					"name": "nub16",
					"parent": "back_right8",
					"pivot": [-9.1, 0.1, 0],
					"cubes": [
						{"origin": [-12.1, -0.4, -1], "size": [2, 2, 2], "uv": [44, 10]}
					]
				},
				{
					"name": "front_right",
					"parent": "tentacles",
					"pivot": [0, 0.1, -5.6],
					"rotation": [0, -7.5, 0],
					"cubes": [
						{"origin": [-2, 0.1, -9.6], "size": [4, 4, 6], "uv": [0, 29]}
					]
				},
				{
					"name": "front_right2",
					"parent": "front_right",
					"pivot": [0, 0.1, -9.1],
					"cubes": [
						{"origin": [-1.5, 0.1, -13.1], "size": [3, 3, 4], "uv": [0, 39]}
					]
				},
				{
					"name": "front_right3",
					"parent": "front_right2",
					"pivot": [0, 0.1, -12.1],
					"cubes": [
						{"origin": [-1, 0.1, -16.1], "size": [2, 2, 4], "uv": [40, 4]}
					]
				},
				{
					"name": "nub",
					"parent": "front_right3",
					"pivot": [0, 0.1, -12.6],
					"cubes": [
						{"origin": [-1, -0.4, -15.6], "size": [2, 2, 2], "inflate": -0.1, "uv": [46, 36]}
					]
				},
				{
					"name": "nub8",
					"parent": "front_right2",
					"pivot": [0, 0.1, -9.1],
					"cubes": [
						{"origin": [-1, -0.4, -12.1], "size": [2, 2, 2], "uv": [40, 44]}
					]
				},
				{
					"name": "neck",
					"parent": "body",
					"pivot": [0, 1, 0],
					"cubes": [
						{"origin": [-3, 4, -3], "size": [6, 4, 6], "uv": [26, 10]}
					]
				},
				{
					"name": "head",
					"parent": "neck",
					"pivot": [0, 1, 0],
					"cubes": [
						{"origin": [-4, 7.5, -4], "size": [8, 8, 8], "uv": [0, 0]}
					]
				},
				{
					"name": "nose",
					"parent": "head",
					"pivot": [0, 1, 0],
					"cubes": [
						{"origin": [-1.5, 10, -7], "size": [3, 3, 3], "uv": [43, 30]},
						{"origin": [-1, 10.5, -7.01], "size": [2, 2, 0], "uv": [24, 0]}
					]
				},
				{
					"name": "eyes",
					"parent": "head",
					"pivot": [-4.1, 13.8, -2.7]
				},
				{
					"name": "left_eye",
					"parent": "eyes",
					"pivot": [4.02, 13.8, -2.7],
					"cubes": [
						{"origin": [4.015, 11.3, -1.7], "size": [0, 3, 1], "uv": [6, 18]},
						{"origin": [4.01, 9.9, -2.7], "size": [0, 4, 3], "uv": [0, 17]},
						{"origin": [4.02, 12.9, -3.1], "size": [0, 2, 4], "pivot": [4.02, 13.9, -2.9], "rotation": [-3, 0, 0], "uv": [0, 0]}
					]
				},
				{
					"name": "right_eye",
					"parent": "eyes",
					"pivot": [0, 1, 0],
					"cubes": [
						{"origin": [-4.1, 12.9, -3.1], "size": [0, 2, 4], "pivot": [-4.1, 13.9, -2.9], "rotation": [-3, 0, 0], "uv": [0, 2]},
						{"origin": [-4.095, 11.3, -1.7], "size": [0, 3, 1], "uv": [6, 15]},
						{"origin": [-4.09, 9.9, -2.7], "size": [0, 4, 3], "uv": [0, 13]}
					]
				},
				{
					"name": "head_nub",
					"parent": "head",
					"pivot": [0, 1, 0],
					"cubes": [
						{"origin": [-1, 15.4, 0.8], "size": [2, 1, 2], "uv": [32, 20]},
						{"origin": [-1, 13.4, 3.7], "size": [2, 2, 1], "uv": [0, 29]},
						{"origin": [-1, 15.4, -2.8], "size": [2, 1, 2], "uv": [36, 34]},
						{"origin": [-1, 13.4, -4.7], "size": [2, 2, 1], "uv": [0, 32]}
					]
				}
			]
		}
	]
}