{
  "name": "cobblemon:battlefactory",
  "order": 0,
  "variations": [
    {
      "aspects": [],
      "poser": "cobblemon:standard",
      "model": "cobblemon:alex.geo",
      "texture": "cobblemon:textures/npcs/battle_factory/factory3.png",
      "layers": []
    },
    {
      "aspects": ["factory"],
      "poser": "cobblemon:standard",
      "model": "cobblemon:alex.geo",
      "texture": "cobblemon:textures/npcs/battle_factory/factory.png",
      "layers": []
    },
    {
      "aspects": ["factory1"],
      "poser": "cobblemon:standard",
      "model": "cobblemon:alex.geo",
      "texture": "cobblemon:textures/npcs/battle_factory/factory1.png",
      "layers": []
    },
    {
      "aspects": ["factory2"],
      "poser": "cobblemon:standard",
      "model": "cobblemon:alex.geo",
      "texture": "cobblemon:textures/npcs/battle_factory/factory2.png",
      "layers": []
    },
    {
      "aspects": ["factor3"],
      "poser": "cobblemon:standard",
      "model": "cobblemon:alex.geo",
      "texture": "cobblemon:textures/npcs/battle_factory/factory6.png",
      "layers": []
    },
    {
      "aspects": ["factory4"],
      "poser": "cobblemon:standard",
      "model": "cobblemon:alex.geo",
      "texture": "cobblemon:textures/npcs/battle_factory/factory4.png",
      "layers": []
    },
        {
      "aspects": ["factory5"],
      "poser": "cobblemon:standard",
      "model": "cobblemon:alex.geo",
      "texture": "cobblemon:textures/npcs/battle_factory/factory5.png",
      "layers": []
    }
  ]
}
