{
    "species": "cobblemon:corsola",
    "order": 1,
    "variations": [
        {
            "aspects": [
            "gym",
            "galarian"
        ],
      "poser": "cobblemon:corsola_galarian",
      "model": "cobblemon:corsola_galar.geo",
        "texture": "cobblemon:textures/pokemon/gym/corsola_galar_gym.png",
        "layers": [
            {
                "name": "transparency",
                "emissive": false,
                "texture": "cobblemon:textures/pokemon/gym/corsola_galar_gym_transparent.png",
                "translucent": true
              }
        ]
    },
    {
        "aspects": [
            "gym",
            "shiny",
            "galarian"
        ],
      "poser": "cobblemon:corsola_galarian",
      "model": "cobblemon:corsola_galar.geo",
        "texture": "cobblemon:textures/pokemon/gym/corsola_galar_gym_shiny.png",
        "Layers": [
            {
                "name": "transparency",
                "emissive": false,
                "texture": "cobblemon:textures/pokemon/gym/corsola_galar_gym_shiny_transparent.png",
                "translucent": true
              }
        ]
    }
    ]
}