{
	"format_version": "1.12.0",
	"minecraft:geometry": [
		{
			"description": {
				"identifier": "geometry.milotic_female",
				"texture_width": 256,
				"texture_height": 256,
				"visible_bounds_width": 8,
				"visible_bounds_height": 9,
				"visible_bounds_offset": [0, -0.5, 0]
			},
			"bones": [
				{
					"name": "milotic",
					"pivot": [0, 0, 0]
				},
				{
					"name": "body",
					"parent": "milotic",
					"pivot": [0, 6, -0.5]
				},
				{
					"name": "neck",
					"parent": "body",
					"pivot": [0, 11, -0.25],
					"cubes": [
						{"origin": [-4, 10, -4.25], "size": [8, 8, 8], "uv": [29, 65]}
					]
				},
				{
					"name": "leg_front_right",
					"parent": "neck",
					"pivot": [2.8, 13.5, -0.9],
					"rotation": [5, 0, 0],
					"cubes": [
						{"origin": [1.3, 6.5, -2.4], "size": [3, 9, 3], "inflate": 0.02, "uv": [60, 107], "mirror": true}
					]
				},
				{
					"name": "leg_front_right2",
					"parent": "leg_front_right",
					"pivot": [2.8, 6.5, 0.1],
					"rotation": [-10, 0, 0],
					"cubes": [
						{"origin": [1.3, 0.5, -2.4], "size": [3, 6, 3], "uv": [26, 110], "mirror": true}
					]
				},
				{
					"name": "leg_front_right3",
					"parent": "leg_front_right2",
					"pivot": [2.8, 1, -1.9],
					"rotation": [5, 0, 0],
					"cubes": [
						{"origin": [1.3, -3.06537, -2.90285], "size": [3, 4, 3], "inflate": -0.02, "uv": [112, 68], "mirror": true}
					]
				},
				{
					"name": "leg_front_left",
					"parent": "neck",
					"pivot": [-2.8, 13.5, -0.9],
					"rotation": [5, 0, 0],
					"cubes": [
						{"origin": [-4.3, 6.5, -2.4], "size": [3, 9, 3], "inflate": 0.02, "uv": [60, 107]}
					]
				},
				{
					"name": "leg_front_left2",
					"parent": "leg_front_left",
					"pivot": [-2.8, 6.5, 0.1],
					"rotation": [-10, 0, 0],
					"cubes": [
						{"origin": [-4.3, 0.5, -2.4], "size": [3, 6, 3], "uv": [26, 110]}
					]
				},
				{
					"name": "leg_front_left3",
					"parent": "leg_front_left2",
					"pivot": [-2.8, 1, -1.9],
					"rotation": [5, 0, 0],
					"cubes": [
						{"origin": [-4.3, -3.06537, -2.90285], "size": [3, 4, 3], "inflate": -0.02, "uv": [112, 68]}
					]
				},
				{
					"name": "neck2",
					"parent": "neck",
					"pivot": [0, 17, -0.25],
					"cubes": [
						{"origin": [-3, 16, -3], "size": [6, 7, 6], "uv": [29, 82]}
					]
				},
				{
					"name": "neck3",
					"parent": "neck2",
					"pivot": [0, 22, 0],
					"cubes": [
						{"origin": [-2.5, 22, -2.5], "size": [5, 6, 5], "uv": [87, 58]},
						{"origin": [2.88674, 22.01, 2.25759], "size": [0, 6, 6], "pivot": [2.88674, 25.51, 4.25759], "rotation": [0, 26, 0], "uv": [109, 85]},
						{"origin": [-2.88674, 22.01, 2.25759], "size": [0, 6, 6], "pivot": [-2.88674, 25.51, 4.25759], "rotation": [0, -26, 0], "uv": [109, 85], "mirror": true}
					]
				},
				{
					"name": "under_neck",
					"parent": "neck3",
					"pivot": [0, 26, -2.5],
					"cubes": [
						{"origin": [-3.5, 26, -7.5], "size": [7, 0, 5], "uv": [43, 101]}
					]
				},
				{
					"name": "under_neck2",
					"parent": "under_neck",
					"pivot": [0, 26, -7.5],
					"cubes": [
						{"origin": [-3.5, 26, -12.5], "size": [7, 0, 5], "uv": [71, 100]}
					]
				},
				{
					"name": "under_neck3",
					"parent": "under_neck2",
					"pivot": [0, 26, -12.5],
					"cubes": [
						{"origin": [-3.5, 26, -15.5], "size": [7, 0, 3], "uv": [108, 64]}
					]
				},
				{
					"name": "neck4",
					"parent": "neck3",
					"pivot": [0, 27, 0],
					"cubes": [
						{"origin": [-2, 27, -2], "size": [4, 5, 4], "inflate": 0.01, "uv": [108, 6]}
					]
				},
				{
					"name": "neck5",
					"parent": "neck4",
					"pivot": [0, 31, 0],
					"cubes": [
						{"origin": [2.88674, 29.01, 1.75759], "size": [0, 6, 5], "pivot": [2.88674, 32.51, 3.75759], "rotation": [0, 26, 0], "uv": [13, 114]},
						{"origin": [-2.88674, 29.01, 1.75759], "size": [0, 6, 5], "pivot": [-2.88674, 32.51, 3.75759], "rotation": [0, -26, 0], "uv": [13, 114], "mirror": true},
						{"origin": [-2, 31, -2], "size": [4, 6, 4], "uv": [43, 107]}
					]
				},
				{
					"name": "head",
					"parent": "neck5",
					"pivot": [0, 36.75, -1]
				},
				{
					"name": "head_correction",
					"parent": "head",
					"pivot": [0, 36.75, -1]
				},
				{
					"name": "head_ai",
					"parent": "head_correction",
					"pivot": [0, 36.75, -1]
				},
				{
					"name": "head_angle",
					"parent": "head_ai",
					"pivot": [0, 36.75, -1],
					"cubes": [
						{"origin": [-3, 34.5, -4.75], "size": [6, 6, 7], "uv": [66, 23]},
						{"origin": [-0.5, 39, -4.8], "size": [1, 1, 0], "uv": [73, 37]},
						{"origin": [-1.5, 35.1, -8.2], "size": [3, 3, 4], "inflate": 0.2, "pivot": [0, 36.6, -6.2], "rotation": [13.25, 0, 0], "uv": [112, 39]}
					]
				},
				{
					"name": "mouth2",
					"parent": "head_angle",
					"pivot": [0, 35.74122, -4.85911],
					"cubes": [
						{"origin": [-1.5, 34.69122, -6.83411], "size": [3, 1, 3], "inflate": 0.1, "uv": [74, 58]}
					]
				},
				{
					"name": "hair2",
					"parent": "head_angle",
					"pivot": [0, 39.175, 0.1],
					"cubes": [
						{"origin": [-2, 37.5, -1.8], "size": [4, 4, 6], "pivot": [0, 39.5, 1.2], "rotation": [5, 0, 0], "uv": [93, 23]}
					]
				},
				{
					"name": "head_hair",
					"parent": "hair2",
					"pivot": [0, 40.5, 0.95],
					"rotation": [35, 0, 0],
					"cubes": [
						{"origin": [0, 40, 0.95], "size": [0, 2, 5], "inflate": 0.01, "uv": [39, 118]}
					]
				},
				{
					"name": "head_hair2",
					"parent": "hair2",
					"pivot": [0, 40.5, 2.7],
					"rotation": [15, 0, 0],
					"cubes": [
						{"origin": [0, 40, 2.7], "size": [0, 2, 7], "uv": [109, 98]}
					]
				},
				{
					"name": "head_hair3",
					"parent": "hair2",
					"pivot": [0, 39.5, 3.95],
					"rotation": [2.5, 0, 0],
					"cubes": [
						{"origin": [0, 38, 3.95], "size": [0, 3, 9], "inflate": 0.01, "uv": [93, 34]}
					]
				},
				{
					"name": "head_hair4",
					"parent": "hair2",
					"pivot": [0, 37.75, 3.2],
					"rotation": [-12.5, 0, 0],
					"cubes": [
						{"origin": [0, 36.25, 3.2], "size": [0, 3, 10], "uv": [75, 84]}
					]
				},
				{
					"name": "head_hair_right",
					"parent": "hair2",
					"pivot": [-2, 39.25, 0.2],
					"rotation": [0, -7.5, 0],
					"cubes": [
						{"origin": [-2, 37.75, 0.2], "size": [0, 3, 8], "uv": [75, 98], "mirror": true}
					]
				},
				{
					"name": "head_hair_left",
					"parent": "hair2",
					"pivot": [2, 39.25, 0.2],
					"rotation": [0, 7.5, 0],
					"cubes": [
						{"origin": [2, 37.75, 0.2], "size": [0, 3, 8], "uv": [75, 98]}
					]
				},
				{
					"name": "ear_left",
					"parent": "head_angle",
					"pivot": [3.25, 37.5, -0.05],
					"rotation": [0, -10, 25],
					"cubes": [
						{"origin": [-0.2574, 35.86262, 0.37177], "size": [6, 9, 0], "uv": [0, 114], "mirror": true}
					]
				},
				{
					"name": "ear_left2",
					"parent": "ear_left",
					"pivot": [3.2426, 44.86262, 0.37177],
					"cubes": [
						{"origin": [0.7426, 44.86262, 0.37177], "size": [5, 9, 0], "uv": [73, 115], "mirror": true}
					]
				},
				{
					"name": "ear_right",
					"parent": "head_angle",
					"pivot": [-3.25, 37.5, -0.05],
					"rotation": [0, 10, -25],
					"cubes": [
						{"origin": [-5.7426, 35.86262, 0.37177], "size": [6, 9, 0], "uv": [0, 114]}
					]
				},
				{
					"name": "ear_right2",
					"parent": "ear_right",
					"pivot": [-3.2426, 44.86262, 0.37177],
					"cubes": [
						{"origin": [-5.7426, 44.86262, 0.37177], "size": [5, 9, 0], "uv": [73, 115]}
					]
				},
				{
					"name": "wisker_left",
					"parent": "head_angle",
					"pivot": [2.7426, 36.36262, -0.62823],
					"cubes": [
						{"origin": [0.7426, 34.86262, -0.62823], "size": [6, 3, 0], "uv": [95, 19], "mirror": true}
					]
				},
				{
					"name": "wisker_left2",
					"parent": "wisker_left",
					"pivot": [6.7426, 34.86262, -0.62823],
					"cubes": [
						{"origin": [6.7426, 34.86262, -0.62823], "size": [6, 3, 0], "uv": [116, 51], "mirror": true}
					]
				},
				{
					"name": "wisker_right",
					"parent": "head_angle",
					"pivot": [-2.7426, 36.36262, -0.62823],
					"cubes": [
						{"origin": [-6.7426, 34.86262, -0.62823], "size": [6, 3, 0], "uv": [95, 19]}
					]
				},
				{
					"name": "wisker_right2",
					"parent": "wisker_right",
					"pivot": [-6.7426, 34.86262, -0.62823],
					"cubes": [
						{"origin": [-12.7426, 34.86262, -0.62823], "size": [6, 3, 0], "uv": [116, 51]}
					]
				},
				{
					"name": "eyes",
					"parent": "head_angle",
					"pivot": [0, 38.75, -3.25],
					"rotation": [5, 0, 0]
				},
				{
					"name": "eye_left",
					"parent": "eyes",
					"pivot": [3.01, 38, -2.75],
					"cubes": [
						{"origin": [3.01, 36.5, -4.25], "size": [0, 3, 3], "uv": [117, 120]}
					]
				},
				{
					"name": "eye_angry_left",
					"parent": "eye_left",
					"pivot": [2.92, 38.5, -3.25],
					"cubes": [
						{"origin": [2.92, 38.25, -4.25], "size": [0, 1, 2], "inflate": 0.01, "uv": [68, 120]},
						{"origin": [2.92, 38.6, -2.25], "size": [0, 1, 1], "inflate": 0.01, "uv": [25, 36]}
					]
				},
				{
					"name": "eye_sad_left",
					"parent": "eye_left",
					"pivot": [2.92, 39, -1.75],
					"cubes": [
						{"origin": [2.92, 38.5, -2.75], "size": [0, 1, 2], "inflate": 0.01, "uv": [102, 122]}
					]
				},
				{
					"name": "pupil_left",
					"parent": "eye_left",
					"pivot": [3.02, 38, -2.75],
					"cubes": [
						{"origin": [3.02, 37, -3.75], "size": [0, 2, 2], "uv": [68, 101]}
					]
				},
				{
					"name": "eyelid_left",
					"parent": "eye_left",
					"pivot": [2.42, 38, -2.75],
					"cubes": [
						{"origin": [1.92, 36.5, -4.25], "size": [1, 3, 3], "inflate": 0.01, "uv": [87, 77]}
					]
				},
				{
					"name": "eyelid_happy_left",
					"parent": "eye_left",
					"pivot": [2.42, 38, -2.75],
					"cubes": [
						{"origin": [1.92, 36.25, -4.25], "size": [1, 3, 3], "inflate": 0.01, "uv": [99, 115]}
					]
				},
				{
					"name": "eyelid_recoil_left",
					"parent": "eye_left",
					"pivot": [2.42, 38, -2.75],
					"cubes": [
						{"origin": [1.92, 36.25, -4.25], "size": [1, 3, 3], "inflate": 0.01, "uv": [50, 118]}
					]
				},
				{
					"name": "eye_right",
					"parent": "eyes",
					"pivot": [-3.01, 38, -2.75],
					"cubes": [
						{"origin": [-3.01, 36.5, -4.25], "size": [0, 3, 3], "uv": [122, 83]}
					]
				},
				{
					"name": "eye_angry_right",
					"parent": "eye_right",
					"pivot": [-2.92, 38.5, -3.25],
					"cubes": [
						{"origin": [-2.92, 38.25, -4.25], "size": [0, 1, 2], "inflate": 0.01, "uv": [122, 112]},
						{"origin": [-2.92, 38.6, -2.25], "size": [0, 1, 1], "inflate": 0.01, "uv": [25, 39]}
					]
				},
				{
					"name": "eye_sad_right",
					"parent": "eye_right",
					"pivot": [-2.92, 39, -1.75],
					"cubes": [
						{"origin": [-2.92, 38.5, -2.75], "size": [0, 1, 2], "inflate": 0.01, "uv": [122, 116]}
					]
				},
				{
					"name": "pupil_right",
					"parent": "eye_right",
					"pivot": [-3.02, 38, -2.75],
					"cubes": [
						{"origin": [-3.02, 37, -3.75], "size": [0, 2, 2], "uv": [33, 120]}
					]
				},
				{
					"name": "eyelid_right",
					"parent": "eye_right",
					"pivot": [-2.42, 38, -2.75],
					"cubes": [
						{"origin": [-2.92, 36.5, -4.25], "size": [1, 3, 3], "inflate": 0.01, "uv": [119, 76]}
					]
				},
				{
					"name": "eyelid_happy_right",
					"parent": "eye_right",
					"pivot": [-2.42, 38, -2.75],
					"cubes": [
						{"origin": [-2.92, 36.25, -4.25], "size": [1, 3, 3], "inflate": 0.01, "uv": [84, 119]}
					]
				},
				{
					"name": "eyelid_recoil_right",
					"parent": "eye_right",
					"pivot": [-2.42, 38, -2.75],
					"cubes": [
						{"origin": [-2.92, 36.25, -4.25], "size": [1, 3, 3], "inflate": 0.01, "uv": [24, 120]}
					]
				},
				{
					"name": "mouth",
					"parent": "head_angle",
					"pivot": [0, 34.85, -4.75]
				},
				{
					"name": "mouth_closed",
					"parent": "mouth",
					"pivot": [0, 34.84, -4.75],
					"cubes": [
						{"origin": [-1.5, 34.84, -5.25], "size": [3, 0, 1], "uv": [74, 63]}
					]
				},
				{
					"name": "mouth_open",
					"parent": "mouth",
					"pivot": [0, 34.94, -4.75],
					"cubes": [
						{"origin": [-1.5, 34.94, -5.75], "size": [3, 0, 2], "uv": [93, 55]}
					]
				},
				{
					"name": "mouth_happy",
					"parent": "mouth",
					"pivot": [0, 34.94, -4.75],
					"cubes": [
						{"origin": [-1.5, 34.94, -5.75], "size": [3, 0, 1], "uv": [122, 95]},
						{"origin": [-1, 34.94, -4.75], "size": [2, 0, 1], "uv": [54, 82]}
					]
				},
				{
					"name": "mouth_sad",
					"parent": "mouth",
					"pivot": [0, 34.94, -4.75],
					"cubes": [
						{"origin": [-1.5, 34.94, -5], "size": [3, 0, 1], "inflate": 0.01, "uv": [122, 108]},
						{"origin": [-1, 34.94, -5.5], "size": [2, 0, 1], "uv": [122, 110]}
					]
				},
				{
					"name": "eyelashes",
					"parent": "head_angle",
					"pivot": [0, 39.5, -4.5],
					"rotation": [10, 0, 0]
				},
				{
					"name": "eyelash_left",
					"parent": "eyelashes",
					"pivot": [3, 38.75, -4.5],
					"rotation": [0, 2.5, 0],
					"cubes": [
						{"origin": [3.01, 38.75, -4.5], "size": [0, 1, 4], "inflate": 0.01, "uv": [59, 120]}
					]
				},
				{
					"name": "eyelash_right",
					"parent": "eyelashes",
					"pivot": [-3, 38.75, -4.5],
					"rotation": [0, -2.5, 0],
					"cubes": [
						{"origin": [-3.01, 38.75, -4.5], "size": [0, 1, 4], "inflate": 0.01, "uv": [108, 120]}
					]
				},
				{
					"name": "hair",
					"parent": "head_angle",
					"pivot": [0, 39.5, 0.25]
				},
				{
					"name": "hair_left1",
					"parent": "hair",
					"pivot": [2, 40, 1.75],
					"cubes": [
						{"origin": [2, 40, 0.25], "size": [4, 0, 3], "uv": [84, 115]}
					]
				},
				{
					"name": "hair_left2",
					"parent": "hair_left1",
					"pivot": [5.5, 40, 1.75],
					"cubes": [
						{"origin": [5.5, 40, -0.25], "size": [5, 0, 4], "uv": [73, 110]}
					]
				},
				{
					"name": "hair_left3",
					"parent": "hair_left2",
					"pivot": [10, 40, 1.75],
					"cubes": [
						{"origin": [10, 40, -0.75], "size": [5, 0, 5], "uv": [108, 0]}
					]
				},
				{
					"name": "hair_left4",
					"parent": "hair_left3",
					"pivot": [14.5, 40, 1.75],
					"cubes": [
						{"origin": [14.5, 40, -1.25], "size": [6, 0, 6], "uv": [70, 16]}
					]
				},
				{
					"name": "hair_left5",
					"parent": "hair_left4",
					"pivot": [20, 40, 1.75],
					"cubes": [
						{"origin": [20, 40, -1.75], "size": [4, 0, 7], "uv": [93, 47]}
					]
				},
				{
					"name": "hair_left6",
					"parent": "hair_left5",
					"pivot": [23.5, 40, 1.75],
					"cubes": [
						{"origin": [23.5, 40, -2.25], "size": [4, 0, 8], "uv": [0, 36]}
					]
				},
				{
					"name": "hair_left7",
					"parent": "hair_left6",
					"pivot": [27, 40, 1.75],
					"cubes": [
						{"origin": [27, 40, -2.75], "size": [11, 0, 9], "uv": [33, 45]}
					]
				},
				{
					"name": "hair_right1",
					"parent": "hair",
					"pivot": [-2, 40, 1.75],
					"cubes": [
						{"origin": [-6, 40, 0.25], "size": [4, 0, 3], "uv": [116, 47]}
					]
				},
				{
					"name": "hair_right2",
					"parent": "hair_right1",
					"pivot": [-5.5, 40, 1.75],
					"cubes": [
						{"origin": [-10.5, 40, -0.25], "size": [5, 0, 4], "uv": [112, 34]}
					]
				},
				{
					"name": "hair_right3",
					"parent": "hair_right2",
					"pivot": [-10, 40, 1.75],
					"cubes": [
						{"origin": [-15, 40, -0.75], "size": [5, 0, 5], "uv": [108, 16]}
					]
				},
				{
					"name": "hair_right4",
					"parent": "hair_right3",
					"pivot": [-14.5, 40, 1.75],
					"cubes": [
						{"origin": [-20.5, 40, -1.25], "size": [6, 0, 6], "uv": [87, 70]}
					]
				},
				{
					"name": "hair_right5",
					"parent": "hair_right4",
					"pivot": [-20, 40, 1.75],
					"cubes": [
						{"origin": [-24, 40, -1.75], "size": [4, 0, 7], "uv": [96, 77]}
					]
				},
				{
					"name": "hair_right6",
					"parent": "hair_right5",
					"pivot": [-23.5, 40, 1.75],
					"cubes": [
						{"origin": [-27.5, 40, -2.25], "size": [4, 0, 8], "uv": [0, 86]}
					]
				},
				{
					"name": "hair_right7",
					"parent": "hair_right6",
					"pivot": [-27, 40, 1.75],
					"cubes": [
						{"origin": [-38, 40, -2.75], "size": [11, 0, 9], "uv": [33, 55]}
					]
				},
				{
					"name": "torso",
					"parent": "body",
					"pivot": [0, 12, -0.5],
					"cubes": [
						{"origin": [-5, 0, -5.5], "size": [10, 12, 10], "uv": [29, 0]}
					]
				},
				{
					"name": "back_hair",
					"parent": "torso",
					"pivot": [0, 6, 4.5],
					"cubes": [
						{"origin": [0, -6, 3.5], "size": [0, 12, 6], "uv": [0, 95]}
					]
				},
				{
					"name": "back_hair2",
					"parent": "back_hair",
					"pivot": [0, -6, 8.5],
					"cubes": [
						{"origin": [0, -18, 3.5], "size": [0, 12, 5], "uv": [96, 1]}
					]
				},
				{
					"name": "back_hair3",
					"parent": "back_hair2",
					"pivot": [0, -18, 4.5],
					"cubes": [
						{"origin": [0, -30, 4.5], "size": [0, 12, 5], "uv": [15, 96]}
					]
				},
				{
					"name": "tail1",
					"parent": "torso",
					"pivot": [0, 1, -0.5],
					"cubes": [
						{"origin": [-4.5, -10, -5], "size": [9, 12, 9], "uv": [29, 23]}
					]
				},
				{
					"name": "leg_left_back4",
					"parent": "tail1",
					"pivot": [4, -5, -2.5],
					"cubes": [
						{"origin": [1.46, -9.04, -6.54], "size": [5.08, 8.08, 7.08], "inflate": 0.04, "uv": [70, 0]}
					]
				},
				{
					"name": "leg_left_back2",
					"parent": "leg_left_back4",
					"pivot": [4, -9.075, -6.525],
					"cubes": [
						{"origin": [2, -16.075, -6.5], "size": [4, 7, 4], "uv": [92, 103]}
					]
				},
				{
					"name": "leg_left_back5",
					"parent": "leg_left_back2",
					"pivot": [4, -16.075, -2.5],
					"cubes": [
						{"origin": [2.5, -24.075, -5.5], "size": [3, 8, 3], "uv": [109, 108]}
					]
				},
				{
					"name": "leg_left_back6",
					"parent": "leg_left_back5",
					"pivot": [4, -24.575, -4],
					"cubes": [
						{"origin": [2.49, -26.085, -7.51], "size": [3.02, 3.02, 5.02], "inflate": 0.01, "uv": [108, 55]}
					]
				},
				{
					"name": "fingers_left",
					"parent": "leg_left_back6",
					"pivot": [4, -24.575, -7.25]
				},
				{
					"name": "finger1_left",
					"parent": "fingers_left",
					"pivot": [4, -24.69824, -6.57375],
					"cubes": [
						{"origin": [2.99, -25.585, -8.76], "size": [2.02, 2.02, 2.02], "inflate": 0.01, "uv": [43, 96]}
					]
				},
				{
					"name": "finger1_left2",
					"parent": "fingers_left",
					"pivot": [4.85, -23.99824, -6.57375],
					"cubes": [
						{"origin": [3.84, -25.885, -7.76], "size": [2.02, 2.02, 2.02], "inflate": 0.01, "uv": [122, 90]}
					]
				},
				{
					"name": "finger1_left3",
					"parent": "fingers_left",
					"pivot": [3.15, -23.99824, -6.57375],
					"cubes": [
						{"origin": [2.14, -25.885, -7.76], "size": [2.02, 2.02, 2.02], "inflate": 0.01, "uv": [93, 122]}
					]
				},
				{
					"name": "leg_right_back4",
					"parent": "tail1",
					"pivot": [-4, -5, -2.5],
					"cubes": [
						{"origin": [-6.54, -9.04, -6.54], "size": [5.08, 8.08, 7.08], "inflate": 0.04, "uv": [70, 0], "mirror": true}
					]
				},
				{
					"name": "leg_right_back2",
					"parent": "leg_right_back4",
					"pivot": [-4, -9.075, -6.525],
					"cubes": [
						{"origin": [-6, -16.075, -6.5], "size": [4, 7, 4], "uv": [92, 103], "mirror": true}
					]
				},
				{
					"name": "leg_right_back5",
					"parent": "leg_right_back2",
					"pivot": [-4, -16.075, -2.5],
					"cubes": [
						{"origin": [-5.5, -24.075, -5.5], "size": [3, 8, 3], "uv": [109, 108], "mirror": true}
					]
				},
				{
					"name": "leg_right_back6",
					"parent": "leg_right_back5",
					"pivot": [-4, -24.575, -4],
					"cubes": [
						{"origin": [-5.51, -26.085, -7.51], "size": [3.02, 3.02, 5.02], "inflate": 0.01, "uv": [108, 55], "mirror": true}
					]
				},
				{
					"name": "fingers_right",
					"parent": "leg_right_back6",
					"pivot": [-4, -24.575, -7.25]
				},
				{
					"name": "finger1_right",
					"parent": "fingers_right",
					"pivot": [-4, -24.69824, -6.57375],
					"cubes": [
						{"origin": [-5.01, -25.585, -8.76], "size": [2.02, 2.02, 2.02], "inflate": 0.01, "uv": [43, 96], "mirror": true}
					]
				},
				{
					"name": "finger1_right2",
					"parent": "fingers_right",
					"pivot": [-4.85, -23.99824, -6.57375],
					"cubes": [
						{"origin": [-5.86, -25.885, -7.76], "size": [2.02, 2.02, 2.02], "inflate": 0.01, "uv": [122, 90], "mirror": true}
					]
				},
				{
					"name": "finger1_right3",
					"parent": "fingers_right",
					"pivot": [-3.15, -23.99824, -6.57375],
					"cubes": [
						{"origin": [-4.16, -25.885, -7.76], "size": [2.02, 2.02, 2.02], "inflate": 0.01, "uv": [93, 122], "mirror": true}
					]
				},
				{
					"name": "tail_center",
					"parent": "tail1",
					"pivot": [0, -9, -0.5],
					"cubes": [
						{"origin": [-4, -19, -4.5], "size": [8, 11, 8], "uv": [0, 45]}
					]
				},
				{
					"name": "tail_center2",
					"parent": "tail_center",
					"pivot": [0, -18, -0.5],
					"cubes": [
						{"origin": [-3.5, -30, -4], "size": [7, 13, 7], "uv": [0, 65]}
					]
				},
				{
					"name": "tail_center2_hair",
					"parent": "tail_center2",
					"pivot": [0, -20.55, 3],
					"cubes": [
						{"origin": [0, -30.05, -2.5], "size": [0, 11, 9], "pivot": [0, -23.55, 4.5], "rotation": [25.5, 0, 0], "uv": [74, 37]}
					]
				},
				{
					"name": "tail_center3",
					"parent": "tail_center2",
					"pivot": [0, -29, -0.5],
					"cubes": [
						{"origin": [-3, -40, -3.5], "size": [6, 12, 6], "uv": [62, 65]}
					]
				},
				{
					"name": "tail_center4",
					"parent": "tail_center3",
					"pivot": [0, -39, -0.5],
					"cubes": [
						{"origin": [-2.5, -49, -3], "size": [5, 11, 5], "uv": [54, 84]}
					]
				},
				{
					"name": "tail_center4_hair",
					"parent": "tail_center4",
					"pivot": [0, -39.875, 2],
					"cubes": [
						{"origin": [0, -50.375, -1], "size": [0, 11, 6], "pivot": [0, -44.875, 2.5], "rotation": [18.25, 0, 0], "uv": [96, 85]}
					]
				},
				{
					"name": "tail_center5",
					"parent": "tail_center4",
					"pivot": [0, -48, -0.25],
					"cubes": [
						{"origin": [-2, -56, -2.5], "size": [4, 9, 4], "uv": [26, 96]}
					]
				},
				{
					"name": "tail_center6",
					"parent": "tail_center5",
					"pivot": [0, -55, -0.5],
					"cubes": [
						{"origin": [-1, -62, -1.95], "size": [2, 7, 3], "uv": [114, 22]}
					]
				},
				{
					"name": "tail_center7",
					"parent": "tail_center6",
					"pivot": [0, -61, -0.5],
					"cubes": [
						{"origin": [-0.5, -66, -1.5], "size": [1, 5, 2], "uv": [66, 37]}
					]
				},
				{
					"name": "tail_center8",
					"parent": "tail_center7",
					"pivot": [0, -66, 0.5],
					"cubes": [
						{"origin": [0, -81, -13.5], "size": [0, 21, 14], "uv": [0, 0]}
					]
				},
				{
					"name": "tail_left",
					"parent": "tail1",
					"pivot": [1, -9, -1.5],
					"cubes": [
						{"origin": [-3, -19, -5.5], "size": [8, 11, 8], "uv": [0, 45]}
					]
				},
				{
					"name": "tail_left2",
					"parent": "tail_left",
					"pivot": [1, -18, -1.5],
					"cubes": [
						{"origin": [-2.5, -30, -5], "size": [7, 13, 7], "uv": [0, 65]}
					]
				},
				{
					"name": "tail_left2_hair",
					"parent": "tail_left2",
					"pivot": [1, -20.55, 2],
					"cubes": [
						{"origin": [1, -30.05, -3.5], "size": [0, 11, 9], "pivot": [1, -23.55, 3.5], "rotation": [25.5, 0, 0], "uv": [74, 37]}
					]
				},
				{
					"name": "tail_left3",
					"parent": "tail_left2",
					"pivot": [1, -29, -1.5],
					"cubes": [
						{"origin": [-2, -40, -4.5], "size": [6, 12, 6], "uv": [62, 65]}
					]
				},
				{
					"name": "tail_left4",
					"parent": "tail_left3",
					"pivot": [1, -39, -1.5],
					"cubes": [
						{"origin": [-1.5, -49, -4], "size": [5, 11, 5], "uv": [54, 84]}
					]
				},
				{
					"name": "tail_left4_hair",
					"parent": "tail_left4",
					"pivot": [1, -39.875, 1],
					"cubes": [
						{"origin": [1, -50.375, -2], "size": [0, 11, 6], "pivot": [1, -44.875, 1.5], "rotation": [18.25, 0, 0], "uv": [96, 85]}
					]
				},
				{
					"name": "tail_left5",
					"parent": "tail_left4",
					"pivot": [1, -48, -1.25],
					"cubes": [
						{"origin": [-1, -56, -3.5], "size": [4, 9, 4], "uv": [26, 96]}
					]
				},
				{
					"name": "tail_left6",
					"parent": "tail_left5",
					"pivot": [1, -55, -1.5],
					"cubes": [
						{"origin": [0, -62, -2.95], "size": [2, 7, 3], "uv": [114, 22]}
					]
				},
				{
					"name": "tail_left7",
					"parent": "tail_left6",
					"pivot": [1, -61, -1.5],
					"cubes": [
						{"origin": [0.5, -66, -2.5], "size": [1, 5, 2], "uv": [66, 37]}
					]
				},
				{
					"name": "tail_left8",
					"parent": "tail_left7",
					"pivot": [1, -66, -0.5],
					"cubes": [
						{"origin": [1, -81, -14.5], "size": [0, 21, 14], "uv": [0, 114]}
					]
				},
				{
					"name": "tail_right",
					"parent": "tail1",
					"pivot": [-1, -9, -1.5],
					"cubes": [
						{"origin": [-5, -19, -5.5], "size": [8, 11, 8], "uv": [0, 45], "mirror": true}
					]
				},
				{
					"name": "tail_right2",
					"parent": "tail_right",
					"pivot": [-1, -18, -1.5],
					"cubes": [
						{"origin": [-4.5, -30, -5], "size": [7, 13, 7], "uv": [0, 65], "mirror": true}
					]
				},
				{
					"name": "tail_right2_hair",
					"parent": "tail_right2",
					"pivot": [-1, -20.55, 2],
					"cubes": [
						{"origin": [-1, -30.05, -3.5], "size": [0, 11, 9], "pivot": [-1, -23.55, 3.5], "rotation": [25.5, 0, 0], "uv": [74, 37], "mirror": true}
					]
				},
				{
					"name": "tail_right3",
					"parent": "tail_right2",
					"pivot": [-1, -29, -1.5],
					"cubes": [
						{"origin": [-4, -40, -4.5], "size": [6, 12, 6], "uv": [62, 65], "mirror": true}
					]
				},
				{
					"name": "tail_right4",
					"parent": "tail_right3",
					"pivot": [-1, -39, -1.5],
					"cubes": [
						{"origin": [-3.5, -49, -4], "size": [5, 11, 5], "uv": [54, 84], "mirror": true}
					]
				},
				{
					"name": "tail_right4_hair",
					"parent": "tail_right4",
					"pivot": [-1, -39.875, 1],
					"cubes": [
						{"origin": [-1, -50.375, -2], "size": [0, 11, 6], "pivot": [-1, -44.875, 1.5], "rotation": [18.25, 0, 0], "uv": [96, 85], "mirror": true}
					]
				},
				{
					"name": "tail_right5",
					"parent": "tail_right4",
					"pivot": [-1, -48, -1.25],
					"cubes": [
						{"origin": [-3, -56, -3.5], "size": [4, 9, 4], "uv": [26, 96], "mirror": true}
					]
				},
				{
					"name": "tail_right6",
					"parent": "tail_right5",
					"pivot": [-1, -55, -1.5],
					"cubes": [
						{"origin": [-2, -62, -2.95], "size": [2, 7, 3], "uv": [114, 22], "mirror": true}
					]
				},
				{
					"name": "tail_right7",
					"parent": "tail_right6",
					"pivot": [-1, -61, -1.5],
					"cubes": [
						{"origin": [-1.5, -66, -2.5], "size": [1, 5, 2], "uv": [66, 37], "mirror": true}
					]
				},
				{
					"name": "tail_right8",
					"parent": "tail_right7",
					"pivot": [-1, -66, -0.5],
					"cubes": [
						{"origin": [-1, -81, -14.5], "size": [0, 21, 14], "uv": [0, 114], "mirror": true}
					]
				}
			]
		}
	]
}