{
  "parent": "minecraft:item/generated",
  "textures": {
    "layer0": "minecraft:item/chainmail_boots"
  },
  "overrides": [
    {
      "predicate": {
        "custom_model_data": 1
      },
      "model": "minecraft:item/armor/st_patricks_boots"
    },
    {
      "predicate": {
        "custom_model_data": 2
      },
      "model": "minecraft:item/armor/ditto_armor_boots"
      },
      {
        "predicate": {
          "custom_model_data": 3
        },
        "model": "minecraft:item/easter2025/easterboots"
      },
      {
        "predicate": {
          "custom_model_data": 4
        },
        "model": "minecraft:item/armor/snow_cloak_boots"
      },
      {
        "predicate": {
          "custom_model_data": 5
        },
        "model": "minecraft:item/armor/black_frost_boots"
      },
      {
        "predicate": {
          "custom_model_data": 6
        },
        "model": "minecraft:item/armor/glacial_boots"
      },
      {
        "predicate": { "custom_model_data": 7 },
        "model": "minecraft:item/star_wars/boba_fett/boots"
      },
      {
        "predicate": { "custom_model_data": 8 },
        "model": "minecraft:item/star_wars/c3po/boots"
      },
      {
        "predicate": { "custom_model_data": 9 },
        "model": "minecraft:item/star_wars/chubaka/boots"
      },
      {
        "predicate": { "custom_model_data": 10 },
        "model": "minecraft:item/star_wars/darth_vader/boots"
      },
      {
        "predicate": { "custom_model_data": 11 },
        "model": "minecraft:item/star_wars/ewok/boots"
      },
      {
        "predicate": { "custom_model_data": 12 },
        "model": "minecraft:item/star_wars/jawas/boots"
      },
      {
        "predicate": { "custom_model_data": 13 },
        "model": "minecraft:item/star_wars/storm_trooper/boots"
      },
      {
        "predicate": { "custom_model_data": 14 },
        "model": "minecraft:item/star_wars/yoda/boots"
      },
      {
        "predicate": { "custom_model_data": 15 },
        "model": "minecraft:item/star_wars/darth_maul/boots"
      },
      {
        "predicate": { "custom_model_data": 16 },
        "model": "minecraft:item/marvel/captain_america/boots"
      },
      {
        "predicate": { "custom_model_data": 17 },
        "model": "minecraft:item/marvel/hulk/boots"
      },
      {
        "predicate": { "custom_model_data": 18 },
        "model": "minecraft:item/marvel/iron_man/boots"
      },
      {
        "predicate": { "custom_model_data": 19 },
        "model": "minecraft:item/marvel/jeff/boots"
      },
      {
        "predicate": { "custom_model_data": 20 },
        "model": "minecraft:item/marvel/moon_knight/boots"
      },
      {
        "predicate": { "custom_model_data": 21 },
        "model": "minecraft:item/marvel/spiderman/boots"
      },
      {
        "predicate": { "custom_model_data": 22 },
        "model": "minecraft:item/marvel/venom/boots"
      },
      {
        "predicate": { "custom_model_data": 23},
        "model": "minecraft:item/beach_set/beachboots"
      },
      {
        "predicate": { "custom_model_data": 24},
        "model": "minecraft:item/summer_animated_weapon_set/armor/boots"
      },
      {
        "predicate": { "custom_model_data": 25},
        "model": "minecraft:item/summer/armor/boots"
      },
      {
        "predicate": { "custom_model_data": 26},
        "model": "minecraft:item/summer/summer_boots"
      }
  ]
}